revkit.cpython-37m-darwin.so
revkit-3.0a2.dev1.dist-info/METADATA
revkit-3.0a2.dev1.dist-info/RECORD
revkit-3.0a2.dev1.dist-info/WHEEL
revkit-3.0a2.dev1.dist-info/top_level.txt
