Metadata-Version: 2.1
Name: revkit
Version: 3.0a2.dev1
Summary: A C++ quantum compilation framework
Home-page: https://msoeken.github.io/revkit.html
Author: Mathias Soeken
Author-email: mathias.soeken@epfl.ch
License: UNKNOWN
Platform: UNKNOWN
Classifier: License :: OSI Approved :: MIT License
Classifier: Operating System :: OS Independent
Requires-Dist: pybind11 (>=2.2)
